silverse/__init__.py
silverse/auth.py
silverse/lib.py
silverse/routes.py
silverse/service.py
silverse/validation.py
silverse/version.py
pysilverse-0.1.2.dist-info/METADATA
pysilverse-0.1.2.dist-info/WHEEL
pysilverse-0.1.2.dist-info/top_level.txt
pysilverse-0.1.2.dist-info/RECORD
