Metadata-Version: 2.1
Name: pysilverse
Version: 0.1.2
Summary: Common Silverse Development Module
Author: Erick Salas
Author-email: it@silversestores.com
Classifier: Programming Language :: Python :: 3
Classifier: License :: OSI Approved :: MIT License
Classifier: Operating System :: OS Independent
Requires-Python: >=3.6
